{
  "Patterns": {
    //"AgencyCode": "Office   :[\\s]{0,5}(?<value>[0-9]{6})",
    //"AgencyCode": "Office   :[\\s\\w{3}]+(?<value>[0-9]{3})",
    "AgencyCode": "Office   :\\s\\w{3}(?<value>\\d{3})", //20220531
    "HarpCode": "Sup\\.code:(?<value>\\s*[0-9]*\\s[0-9]*)",
    "ClientCode": "Cust\\.nr:[\\s]{0,7}(?<value>[0-9]{1,7})",
    "DocumentId": "Reference:[\\s]{0,3}[A-Z]{1}(?<value>[0-9]{7})",
    "DocumentIssueDate": "Date Iss\\.:[\\s]{0,5}(?<value>[0-9]{1,2}/[0-9]{1,2}/[0-9]{2,4})",
    "PassengerName": "Name:(?<value>[\\s]{0,1}[A-Z\\/]+)",
    "VoucherNumber": "Number   :[\\s]{0,3}(?<voucherSeries>[a-zA-Z0-9]{1,2})[\\s\\-]{1,2}(?<voucherNumber>[0-9]{9})",
    "VoucherType": "PURCHASE HOTEL|HOTEL PREPAID|HOTEL REFERRAL",
    "VoucherSeriesType": "29|56|3C",
    "WingsProduct": "Product  :(?<value>\\s*[A-Z0-9]*)",
    "SupplierDescription": "To  :[\\s]{0,3}(?<value>[A-Z\\w]{1,20}[\\s]{0,1}[A-Z\\w]{1,20}[\\s]{0,1}[A-Z\\w]{1,20}[\\s]{0,1}[A-Z\\w]{1,20}[\\s]{0,1})",
    "SupplierFax_1": "Fax :[\\s]{0,3}(?<value>[(]{0,1}[0-9]{0,4}[)]{0,1}[\\s]{0,3}[0-9]{0,4}[\\s]{0,3}[0-9]{0,10}[\\s]{0,3}[0-9]{0,10}[\\s]{0,3}[0-9]{0,10}[\\s]{0,3}[0-9]{0,10}[\\s]{0,3}[0-9]{0,10})",
    "SupplierFax_2": "Fax :[\\s]{0,3}(?<value>[0-9\\+\\(\\)\\/]{1,20}[\\s]{0,3}[0-9\\+\\(\\)\\/]{1,20}[\\s]{0,3}[0-9\\+\\(\\)\\/]{1,20}[\\s]{0,3}[0-9\\+\\(\\)\\/]{1,20}[\\s]{0,3}[0-9\\+\\(\\)\\/]{1,20})",
    "DataIn": "Arr\\.date:[\\s]{0,5}(?<value>[0-9]{1,2}\\/[0-9]{1,2}\\/[0-9]{2,4})",
    "DataOut": "Dep\\.date:[\\s]{0,5}(?<value>[0-9]{1,2}\\/[0-9]{1,2}\\/[0-9]{2,4})",
    "TotalAmount": "Tot\\.EUR[\\s]{0,15}(?<value>[0-9]{1,5},[0-9]{1,2})",
    "Commission": "Commission :",
    "Discount": "Discount   :"
  },
  "FoldersPath": {
    /*
    "Original": "\\\\swrom1xb03023\\EmeaFTP\\Voucher\\",
    "Processed": "\\\\vwedc2if00777\\italy\\backoffice\\WingsManager\\Voucher\\",
    "Error": "\\\\vwedc2if00777\\italy\\backoffice\\WingsManager\\Voucher\\Errati\\"
    */
    "Original": "C:\\BackofficeStorage\\EmeaFTP\\Voucher\\",
    "Processed": "C:\\BackofficeStorage\\Voucher\\Acquisiti\\",
    "Error": "C:\\BackofficeStorage\\Voucher\\Errati\\"
  }
}
